{
  "rasa_nlu_data": {
    "regex_features": [],
    "entity_synonyms": [],
    "common_examples": [
      {
        "text": "show me scream",
        "intent": "find_by_title",
        "entities": [
          {
            "end": 14,
            "start": 8,
            "entity": "paint",
            "value": "scream"
          }
        ]
      },
      {
        "text": "i want to see scream",
        "intent": "find_by_title",
        "entities": [
          {
            "end": 20,
            "start": 14,
            "entity": "paint",
            "value": "scream"
          }
        ]
      },
      {
        "text": "show me a picture painted by munch",
        "intent": "find_by_author",
        "entities": [
          {
            "end": 34,
            "start": 29,
            "entity": "paint",
            "value": "munch"
          }
        ]
      },
      {
        "text": "get picture of munch",
        "intent": "find_by_author",
        "entities": [
          {
            "end": 20,
            "start": 15,
            "entity": "paint",
            "value": "munch"
          }
        ]
      }
    ]
  }
}